[
    {
        "id": 1,
        "name": "Jose Maria Sosa",
        "email": "jose_skedar@hotmail.com",
        "dateOfBirth": "1988-05-21"
    },
    {
        "id": 2,
        "name": "Leonardo Ulloa",
        "email": "leo_ulloa@hotmail.com",
        "dateOfBirth": "1987-05-21"
    },
    {
        "id": 3,
        "name": "Andres Santo",
        "email": "santiago@gmail.com",
        "dateOfBirth": "1990-12-10"
    },
    {
        "id": 4,
        "name": "Alma Sandoval",
        "email": "almasan@gmail.com",
        "dateOfBirth": "1984-07-14"
    },
    {
        "id": 5,
        "name": "Alexa Clark",
        "email": "alexa_clark@gmail.com",
        "dateOfBirth": "1991-06-20"
    }
]
